printnanny_octoprint_models/CurrentJob.py
printnanny_octoprint_models/Filament.py
printnanny_octoprint_models/GcodeEvent.py
printnanny_octoprint_models/GcodeFile.py
printnanny_octoprint_models/Job.py
printnanny_octoprint_models/JobProgress.py
printnanny_octoprint_models/JobProgressChanged.py
printnanny_octoprint_models/JobStatus.py
printnanny_octoprint_models/JobStatusChanged.py
printnanny_octoprint_models/OctoPrintGcode.py
printnanny_octoprint_models/OctoPrintServerStatus.py
printnanny_octoprint_models/OctoPrintServerStatusChanged.py
printnanny_octoprint_models/PrinterStatus.py
printnanny_octoprint_models/PrinterStatusChanged.py
printnanny_octoprint_models/__init__.py
printnanny_octoprint_models-0.1.9.dist-info/METADATA
printnanny_octoprint_models-0.1.9.dist-info/WHEEL
printnanny_octoprint_models-0.1.9.dist-info/top_level.txt
printnanny_octoprint_models-0.1.9.dist-info/RECORD
